<templateSet group="Zen CSS">
  <template name="@mx" value=" @media screen and (max-width: $END$px) {&#10; &#10; }" description="@media max-width" toReformat="false" toShortenFQNames="true">
    <context>
      <option name="CSS" value="true" />
    </context>
  </template>
  <template name="clg" value="console.log('$LOG$');" description="console.log" toReformat="false" toShortenFQNames="true">
    <variable name="LOG" expression="" defaultValue="" alwaysStopAt="true" />
    <context>
      <option name="JAVA_SCRIPT" value="true" />
    </context>
  </template>
</templateSet>